aurora/__init__.py
aurora/helpers.py
aurora/core/__init__.py
aurora/core/types.py
aurora/core/autodiff/__init__.py
aurora/core/autodiff/backends.py
aurora/core/autodiff/gradient.py
aurora/core/autodiff/hessian.py
aurora/core/autodiff/jacobian.py
aurora/core/autodiff/products.py
aurora/core/autodiff/utils.py
aurora/core/backends/__init__.py
aurora/core/backends/_protocol.py
aurora/core/backends/_registry.py
aurora/core/backends/jax_backend.py
aurora/core/backends/operations.py
aurora/core/backends/pytorch_backend.py
aurora/core/linalg/__init__.py
aurora/core/optimization/__init__.py
aurora/core/optimization/base.py
aurora/core/optimization/irls.py
aurora/core/optimization/lbfgs.py
aurora/core/optimization/newton.py
aurora/core/optimization/result.py
aurora/core/optimization/sparse_solvers.py
aurora/distributions/__init__.py
aurora/distributions/_utils.py
aurora/distributions/base.py
aurora/distributions/custom/__init__.py
aurora/distributions/families/__init__.py
aurora/distributions/families/beta.py
aurora/distributions/families/binomial.py
aurora/distributions/families/gamma.py
aurora/distributions/families/gaussian.py
aurora/distributions/families/inverse_gaussian.py
aurora/distributions/families/negative_binomial.py
aurora/distributions/families/poisson.py
aurora/distributions/families/student_t.py
aurora/distributions/families/tweedie.py
aurora/distributions/links/__init__.py
aurora/distributions/links/common.py
aurora/estimation/__init__.py
aurora/estimation/laplace/__init__.py
aurora/estimation/ml/__init__.py
aurora/estimation/reml/__init__.py
aurora/inference/__init__.py
aurora/inference/robust.py
aurora/inference/anova/__init__.py
aurora/inference/diagnostics/__init__.py
aurora/inference/diagnostics/glm.py
aurora/inference/hypothesis/__init__.py
aurora/inference/hypothesis/wald.py
aurora/inference/intervals/__init__.py
aurora/inference/intervals/confidence.py
aurora/io/__init__.py
aurora/io/converters/__init__.py
aurora/io/readers/__init__.py
aurora_glm-0.7.0.dist-info/licenses/AUTHORS.txt
aurora_glm-0.7.0.dist-info/licenses/LICENSE
aurora_glm-0.7.0.dist-info/METADATA
aurora_glm-0.7.0.dist-info/WHEEL
aurora_glm-0.7.0.dist-info/top_level.txt
aurora_glm-0.7.0.dist-info/RECORD
