Metadata-Version: 2.4
Name: aurora-glm
Version: 0.7.0
Summary: A modular, extensible, and high-performance Python framework for generalized linear models (GLM), generalized additive models (GAM), and generalized additive mixed models (GAMM)
Author-email: "Lucy E. Arias" <mat.eduardo.arias@outlook.com>
License: MIT
Project-URL: Homepage, https://github.com/Matcraft94/Aurora-GLM
Project-URL: Repository, https://github.com/Matcraft94/Aurora-GLM
Project-URL: Documentation, https://github.com/Matcraft94/Aurora-GLM
Keywords: glm,gam,gamm,statistics,regression,generalized-linear-models,additive-models,mixed-models,splines,smoothing,bayesian,count-models,zero-inflated,hurdle-models,multi-backend,gpu-acceleration,pytorch,jax,numpy
Classifier: Intended Audience :: Science/Research
Classifier: Intended Audience :: Developers
Classifier: License :: OSI Approved :: MIT License
Classifier: Operating System :: OS Independent
Classifier: Programming Language :: Python :: 3
Classifier: Programming Language :: Python :: 3.10
Classifier: Programming Language :: Python :: 3.11
Classifier: Programming Language :: Python :: 3.12
Classifier: Topic :: Scientific/Engineering
Classifier: Topic :: Scientific/Engineering :: Mathematics
Classifier: Topic :: Scientific/Engineering :: Information Analysis
Classifier: Topic :: Scientific/Engineering :: Artificial Intelligence
Classifier: Typing :: Typed
Requires-Python: >=3.10
License-File: LICENSE
License-File: AUTHORS.txt
Requires-Dist: numpy==2.3.3
Requires-Dist: scipy==1.16.3
Requires-Dist: pandas==2.3.3
Requires-Dist: statsmodels==0.14.5
Requires-Dist: matplotlib==3.10.7
Requires-Dist: pillow==11.3.0
Requires-Dist: python-dateutil==2.9.0.post0
Requires-Dist: pytz==2025.2
Requires-Dist: packaging==25.0
Requires-Dist: pyparsing==3.2.5
Requires-Dist: cycler==0.12.1
Requires-Dist: kiwisolver==1.4.9
Requires-Dist: contourpy==1.3.3
Requires-Dist: fonttools==4.60.1
Requires-Dist: mpmath==1.3.0
Requires-Dist: networkx==3.5
Requires-Dist: sympy==1.14.0
Requires-Dist: typing_extensions==4.15.0
Provides-Extra: torch
Requires-Dist: torch>=2.0.0; extra == "torch"
Requires-Dist: torchvision>=0.15.0; extra == "torch"
Provides-Extra: jax
Requires-Dist: jax>=0.4.0; extra == "jax"
Requires-Dist: jaxlib>=0.4.0; extra == "jax"
Provides-Extra: bayesian
Requires-Dist: numpyro>=0.13.0; extra == "bayesian"
Requires-Dist: pymc>=5.0.0; extra == "bayesian"
Requires-Dist: arviz>=0.16.0; extra == "bayesian"
Provides-Extra: benchmarks
Requires-Dist: psutil>=5.9.0; extra == "benchmarks"
Requires-Dist: rpy2>=3.5.0; extra == "benchmarks"
Provides-Extra: dev
Requires-Dist: pytest>=8.0.0; extra == "dev"
Requires-Dist: pytest-cov>=4.0.0; extra == "dev"
Requires-Dist: coverage>=7.0.0; extra == "dev"
Requires-Dist: ruff>=0.1.0; extra == "dev"
Requires-Dist: mypy>=1.0.0; extra == "dev"
Requires-Dist: scikit-learn>=1.0.0; extra == "dev"
Provides-Extra: all
Requires-Dist: torch>=2.0.0; extra == "all"
Requires-Dist: torchvision>=0.15.0; extra == "all"
Requires-Dist: jax>=0.4.0; extra == "all"
Requires-Dist: jaxlib>=0.4.0; extra == "all"
Requires-Dist: numpyro>=0.13.0; extra == "all"
Requires-Dist: pymc>=5.0.0; extra == "all"
Requires-Dist: arviz>=0.16.0; extra == "all"
Requires-Dist: psutil>=5.9.0; extra == "all"
Requires-Dist: rpy2>=3.5.0; extra == "all"
Dynamic: license-file
